odoo/addons/sale_import_base/README.rst
odoo/addons/sale_import_base/__init__.py
odoo/addons/sale_import_base/__manifest__.py
odoo/addons/sale_import_base/data/sale_exception.xml
odoo/addons/sale_import_base/demo/demo.xml
odoo/addons/sale_import_base/i18n/it.po
odoo/addons/sale_import_base/i18n/sale_import_base.pot
odoo/addons/sale_import_base/migrations/16.0.2.0.0/post-migration.py
odoo/addons/sale_import_base/migrations/16.0.2.0.0/pre-migration.py
odoo/addons/sale_import_base/models/__init__.py
odoo/addons/sale_import_base/models/payment_provider.py
odoo/addons/sale_import_base/models/sale_channel.py
odoo/addons/sale_import_base/models/sale_channel_importer.py
odoo/addons/sale_import_base/models/sale_import_payload.py
odoo/addons/sale_import_base/models/sale_order.py
odoo/addons/sale_import_base/models/schemas.py
odoo/addons/sale_import_base/pydantic/__init__.py
odoo/addons/sale_import_base/readme/CONTRIBUTORS.rst
odoo/addons/sale_import_base/readme/DESCRIPTION.rst
odoo/addons/sale_import_base/readme/USAGE.rst
odoo/addons/sale_import_base/security/ir.model.access.csv
odoo/addons/sale_import_base/security/ir_rule.xml
odoo/addons/sale_import_base/security/res_groups.xml
odoo/addons/sale_import_base/static/description/icon.png
odoo/addons/sale_import_base/static/description/index.html
odoo/addons/sale_import_base/tests/__init__.py
odoo/addons/sale_import_base/tests/common_sale_order_import.py
odoo/addons/sale_import_base/tests/data.py
odoo/addons/sale_import_base/tests/test_sale_order_import.py
odoo/addons/sale_import_base/views/payment_provider_view.xml
odoo/addons/sale_import_base/views/sale_channel_view.xml
odoo/addons/sale_import_base/views/sale_import_payload.xml
odoo_addon_sale_import_base-16.0.2.0.1.1.dist-info/METADATA
odoo_addon_sale_import_base-16.0.2.0.1.1.dist-info/WHEEL
odoo_addon_sale_import_base-16.0.2.0.1.1.dist-info/top_level.txt
odoo_addon_sale_import_base-16.0.2.0.1.1.dist-info/RECORD
