Metadata-Version: 2.1
Name: odoo-addon-sale_import_base
Version: 16.0.2.0.1.1
Summary: Base for importing Sale Orders through a JSON file format
Home-page: https://github.com/OCA/sale-channel
Author: Akretion, Odoo Community Association (OCA)
Author-email: support@odoo-community.org
License: AGPL-3
Classifier: Programming Language :: Python
Classifier: Framework :: Odoo
Classifier: Framework :: Odoo :: 16.0
Classifier: License :: OSI Approved :: GNU Affero General Public License v3
Requires-Python: >=3.10
Requires-Dist: extendable-pydantic
Requires-Dist: odoo-addon-extendable<16.1dev,>=16.0dev
Requires-Dist: odoo-addon-queue-job<16.1dev,>=16.0dev
Requires-Dist: odoo-addon-sale-channel-partner<16.1dev,>=16.0dev
Requires-Dist: odoo-addon-sale-exception<16.1dev,>=16.0dev
Requires-Dist: odoo<16.1dev,>=16.0a
Requires-Dist: openupgradelib
